tree_sitter_gstlaunch-0.1.0.dist-info/top_level.txt
tree_sitter_gstlaunch-0.1.0.dist-info/METADATA
tree_sitter_gstlaunch-0.1.0.dist-info/WHEEL
tree_sitter_gstlaunch-0.1.0.dist-info/RECORD
tree_sitter_gstlaunch-0.1.0.dist-info/LICENSE
tree_sitter_gstlaunch/binding.c
tree_sitter_gstlaunch/__init__.py
tree_sitter_gstlaunch/py.typed
tree_sitter_gstlaunch/__init__.pyi
tree_sitter_gstlaunch/_binding.abi3.so
