Metadata-Version: 2.1
Name: tree-sitter-gstlaunch
Version: 0.1.0
Summary: Gstlaunch grammar for tree-sitter
License: MIT
Project-URL: Homepage, https://github.com/tree-sitter-grammars/tree-sitter-gstlaunch
Keywords: incremental,parsing,tree-sitter,gstlaunch
Classifier: Intended Audience :: Developers
Classifier: License :: OSI Approved :: MIT License
Classifier: Topic :: Software Development :: Compilers
Classifier: Topic :: Text Processing :: Linguistic
Classifier: Typing :: Typed
Requires-Python: >=3.8
License-File: LICENSE
Provides-Extra: core
Requires-Dist: tree-sitter ~=0.21 ; extra == 'core'
